beerxml/__init__.py
beerxml/beerxml_parser.py
beerxml/models.py
beerxml-0.0.8.dist-info/LICENSE
beerxml-0.0.8.dist-info/METADATA
beerxml-0.0.8.dist-info/WHEEL
beerxml-0.0.8.dist-info/RECORD
